rail_score/__init__.py
rail_score/client.py
rail_score/compliance.py
rail_score/evaluation.py
rail_score/exceptions.py
rail_score/generation.py
rail_score/models.py
rail_score-1.0.1.dist-info/licenses/LICENSE
rail_score-1.0.1.dist-info/METADATA
rail_score-1.0.1.dist-info/WHEEL
rail_score-1.0.1.dist-info/top_level.txt
rail_score-1.0.1.dist-info/RECORD
