Metadata-Version: 2.4
Name: rail-score
Version: 1.0.1
Summary: Official Python SDK for RAIL Score API - Evaluate and generate responsible AI content
Home-page: https://github.com/Responsible-AI-Labs/rail-score
Author: Responsible AI Labs
Author-email: Responsible AI Labs <support@responsibleailabs.ai>
Maintainer-email: Responsible AI Labs <support@responsibleailabs.ai>
License: MIT
Project-URL: Homepage, https://responsibleailabs.ai
Project-URL: Documentation, https://responsibleailabs.ai/docs
Project-URL: Repository, https://github.com/Responsible-AI-Labs/rail-score
Project-URL: Bug Tracker, https://github.com/Responsible-AI-Labs/rail-score/issues
Project-URL: Source Code, https://github.com/Responsible-AI-Labs/rail-score
Project-URL: Changelog, https://github.com/Responsible-AI-Labs/rail-score/blob/main/CHANGELOG.md
Project-URL: API Reference, https://responsibleailabs.ai/docs/api
Keywords: responsible-ai,rail-score,ai-evaluation,ai-safety,compliance,gdpr,hipaa,ccpa,eu-ai-act,ai-ethics,content-moderation,rag-evaluation,hallucination-detection,ai-governance,trustworthy-ai,fairness,transparency,accountability,privacy,ai-assessment
Classifier: Development Status :: 4 - Beta
Classifier: Intended Audience :: Developers
Classifier: Intended Audience :: Science/Research
Classifier: Intended Audience :: Information Technology
Classifier: Topic :: Scientific/Engineering :: Artificial Intelligence
Classifier: Topic :: Software Development :: Libraries :: Python Modules
Classifier: Topic :: Security
Classifier: Topic :: Internet :: WWW/HTTP :: Dynamic Content
Classifier: License :: OSI Approved :: MIT License
Classifier: Programming Language :: Python :: 3
Classifier: Programming Language :: Python :: 3.8
Classifier: Programming Language :: Python :: 3.9
Classifier: Programming Language :: Python :: 3.10
Classifier: Programming Language :: Python :: 3.11
Classifier: Programming Language :: Python :: 3.12
Classifier: Operating System :: OS Independent
Classifier: Typing :: Typed
Requires-Python: >=3.8
License-File: LICENSE
Requires-Dist: requests>=2.28.0
Provides-Extra: dev
Requires-Dist: pytest>=7.0.0; extra == "dev"
Requires-Dist: pytest-cov>=4.0.0; extra == "dev"
Requires-Dist: black>=22.0.0; extra == "dev"
Requires-Dist: mypy>=0.990; extra == "dev"
Requires-Dist: isort>=5.11.0; extra == "dev"
Requires-Dist: flake8>=5.0.0; extra == "dev"
Requires-Dist: types-requests>=2.28.0; extra == "dev"
Provides-Extra: docs
Requires-Dist: sphinx>=5.0.0; extra == "docs"
Requires-Dist: sphinx-rtd-theme>=1.0.0; extra == "docs"
Requires-Dist: sphinx-autodoc-typehints>=1.19.0; extra == "docs"
Provides-Extra: all
Requires-Dist: rail-score[dev,docs]; extra == "all"
Dynamic: author
Dynamic: home-page
Dynamic: license-file
Dynamic: requires-python
